cli/__init__.py
cli/download_cli.py
cli/main.py
cli/mixcloud_cli.py
cli/organize_cli.py
cli/test_cli.py
config/__init__.py
config/default_settings.py
config/settings.py
core/__init__.py
core/color_utils.py
core/cover_utils.py
core/file_utils.py
core/metadata_utils.py
core/version.py
modules/__init__.py
modules/covers/__init__.py
modules/covers/create_album_cover.py
modules/download/__init__.py
modules/download/download_pexel.py
modules/download/downloader.py
modules/download/post_process.py
modules/mixcloud/__init__.py
modules/mixcloud/uploader.py
modules/organize/__init__.py
modules/organize/organize_files.py
djautomation-1.8.0a0.dist-info/LICENSE
djautomation-1.8.0a0.dist-info/METADATA
djautomation-1.8.0a0.dist-info/WHEEL
djautomation-1.8.0a0.dist-info/entry_points.txt
djautomation-1.8.0a0.dist-info/top_level.txt
djautomation-1.8.0a0.dist-info/RECORD
