Metadata-Version: 2.2
Name: djautomation
Version: 1.8.0a0
Summary: A CLI for DJ automation workflows.
Home-page: https://github.com/Katazui/DJAutomation
Author: Katazui
Author-email: FootLong@Duck.com
Project-URL: Source, https://github.com/Katazui/DJAutomation
Project-URL: Tracker, https://github.com/Katazui/DJAutomation/issues
Classifier: Programming Language :: Python :: 3
Classifier: Programming Language :: Python :: 3.7
Classifier: Programming Language :: Python :: 3.8
Classifier: Programming Language :: Python :: 3.9
Classifier: Programming Language :: Python :: 3.10
Classifier: License :: OSI Approved :: MIT License
Classifier: Operating System :: OS Independent
Classifier: Intended Audience :: Developers
Classifier: Topic :: Software Development :: Libraries :: Python Modules
Classifier: Topic :: Utilities
Requires-Python: >=3.7
License-File: LICENSE
Requires-Dist: yt-dlp
Requires-Dist: mutagen
Requires-Dist: requests
Requires-Dist: Pillow
Requires-Dist: python-dotenv
Requires-Dist: pytz
Requires-Dist: Send2Trash
Requires-Dist: pytest
Dynamic: author
Dynamic: author-email
Dynamic: classifier
Dynamic: description
Dynamic: description-content-type
Dynamic: home-page
Dynamic: project-url
Dynamic: requires-dist
Dynamic: requires-python
Dynamic: summary
